math_operations/__init__.py
math_operations/addition.py
math_operations/division.py
math_operations/multiplication.py
math_operations/subtraction.py
math_operations_sethu-0.1.dist-info/METADATA
math_operations_sethu-0.1.dist-info/WHEEL
math_operations_sethu-0.1.dist-info/top_level.txt
math_operations_sethu-0.1.dist-info/RECORD
