Metadata-Version: 2.1
Name: math_operations_sethu
Version: 0.1
Summary: A package for basic arithmetic operations
Home-page: https://github.com/senathipathi-i2i/math_operation
Author: senathipathi
Author-email: senathipathi.vinayagam@ideas2it.com
Classifier: Programming Language :: Python :: 3
Classifier: License :: OSI Approved :: MIT License
Classifier: Operating System :: OS Independent
Requires-Python: >=3.6
